cryptodemo/__init__.py
cryptodemo-0.0.1.dist-info/LICENSE
cryptodemo-0.0.1.dist-info/METADATA
cryptodemo-0.0.1.dist-info/WHEEL
cryptodemo-0.0.1.dist-info/top_level.txt
cryptodemo-0.0.1.dist-info/RECORD
