Metadata-Version: 2.1
Name: cryptodemo
Version: 0.0.1
Summary: cryptography practice demo.
Home-page: https://github.com/istommao/cryptodemo
Author: silence
Author-email: istommao@gmail.com
License: UNKNOWN
Keywords: cryptography practice demo!
Platform: UNKNOWN
